teslastruct/_utils.py
teslastruct/frozen.py
teslastruct/hashable.py
teslastruct/nothing.py
teslastruct/onChangeLite.py
teslastruct/onChangeV1.py
teslastruct/singletonV1.py
teslastruct-0.1.0.dist-info/METADATA
teslastruct-0.1.0.dist-info/WHEEL
teslastruct-0.1.0.dist-info/licenses/LICENSE
teslastruct-0.1.0.dist-info/RECORD
