Metadata-Version: 2.3
Name: teslastruct
Version: 0.1.0
Summary: Unconventional utils and data structures
Author-email: ZackaryW <36378555+ZackaryW@users.noreply.github.com>
License-File: LICENSE
Requires-Python: >=3.8
